yemot/__init__.py
yemot/campaign.py
yemot/client.py
yemot/system.py
yemot-0.1.2.dist-info/METADATA
yemot-0.1.2.dist-info/WHEEL
yemot-0.1.2.dist-info/RECORD
