Metadata-Version: 2.4
Name: yemot
Version: 0.1.2
Summary: Python client for the Yemot (Call2All) API
Author-email: davidTheDeveloper <dev@code-chai.com>
Requires-Python: >=3.11
Requires-Dist: requests>=2.32.5
